hiosint/__init__.py
hiosint/cli.py
hiosint/core.py
hiosint/modules/__init__.py
hiosint/modules/leaks/__init__.py
hiosint/modules/leaks/dehashed.py
hiosint/modules/leaks/leakcheck.py
hiosint/modules/leaks/snusbase.py
hiosint/modules/search_engines/__init__.py
hiosint/modules/search_engines/duckduckgo.py
hiosint/modules/search_engines/google.py
hiosint-1.2.0.dist-info/LICENSE.md
hiosint-1.2.0.dist-info/METADATA
hiosint-1.2.0.dist-info/WHEEL
hiosint-1.2.0.dist-info/entry_points.txt
hiosint-1.2.0.dist-info/RECORD
